[
  {
    "sku":"LGT-ARC-001",
    "title":"ArcFloor Lamp",
    "category":"Lighting",
    "price":129,
    "style":"Modern",
    "tags":[
      "modern",
      "steel",
      "floor"
    ],
    "url":"https:\/\/example.com\/arcfloor",
    "image_url":"https:\/\/via.placeholder.com\/600?text=ArcFloor+Lamp",
    "aisle":"A3",
    "bay":"12",
    "qty_on_hand":2
  },
  {
    "sku":"LGT-TBL-002",
    "title":"Loft Table Lamp",
    "category":"Lighting",
    "price":89,
    "style":"Industrial",
    "tags":[
      "industrial",
      "matte-black",
      "table"
    ],
    "url":"https:\/\/example.com\/loft-table",
    "image_url":"https:\/\/via.placeholder.com\/600?text=Loft+Table+Lamp",
    "aisle":"A3",
    "bay":"08",
    "qty_on_hand":5
  },
  {
    "sku":"LGT-PND-003",
    "title":"Nimbus Pendant",
    "category":"Lighting",
    "price":149,
    "style":"Minimalist",
    "tags":[
      "minimalist",
      "pendant",
      "brushed"
    ],
    "url":"https:\/\/example.com\/nimbus-pendant",
    "image_url":"https:\/\/via.placeholder.com\/600?text=Nimbus+Pendant",
    "aisle":"A2",
    "bay":"04",
    "qty_on_hand":0
  },
  {
    "sku":"LGT-STR-004",
    "title":"Strand Rattan Lamp",
    "category":"Lighting",
    "price":59,
    "style":"Boho",
    "tags":[
      "boho",
      "rattan",
      "table"
    ],
    "url":"https:\/\/example.com\/strand-rattan",
    "image_url":"https:\/\/via.placeholder.com\/600?text=Strand+Rattan",
    "aisle":"A4",
    "bay":"09",
    "qty_on_hand":7
  },
  {
    "sku":"LGT-SEA-005",
    "title":"Harbor Sconce",
    "category":"Lighting",
    "price":79,
    "style":"Coastal",
    "tags":[
      "coastal",
      "brass",
      "wall"
    ],
    "url":"https:\/\/example.com\/harbor-sconce",
    "image_url":"https:\/\/via.placeholder.com\/600?text=Harbor+Sconce",
    "aisle":"A2",
    "bay":"10",
    "qty_on_hand":3
  },
  {
    "sku":"SEA-LNG-101",
    "title":"Grove Lounge Chair",
    "category":"Seating",
    "price":199,
    "style":"Modern",
    "tags":[
      "modern",
      "fabric",
      "lounge"
    ],
    "url":"https:\/\/example.com\/grove-lounge",
    "image_url":"https:\/\/via.placeholder.com\/600?text=Grove+Lounge+Chair",
    "aisle":"B1",
    "bay":"03",
    "qty_on_hand":4
  },
  {
    "sku":"SEA-BAR-102",
    "title":"Forge Bar Stool",
    "category":"Seating",
    "price":69,
    "style":"Industrial",
    "tags":[
      "industrial",
      "metal",
      "stool"
    ],
    "url":"https:\/\/example.com\/forge-stool",
    "image_url":"https:\/\/via.placeholder.com\/600?text=Forge+Bar+Stool",
    "aisle":"B2",
    "bay":"06",
    "qty_on_hand":12
  },
  {
    "sku":"SEA-OTM-103",
    "title":"Cloud Ottoman",
    "category":"Seating",
    "price":89,
    "style":"Minimalist",
    "tags":[
      "minimalist",
      "ottoman",
      "foam"
    ],
    "url":"https:\/\/example.com\/cloud-ottoman",
    "image_url":"https:\/\/via.placeholder.com\/600?text=Cloud+Ottoman",
    "aisle":"B3",
    "bay":"11",
    "qty_on_hand":1
  },
  {
    "sku":"SEA-BEN-104",
    "title":"Willow Bench",
    "category":"Seating",
    "price":129,
    "style":"Boho",
    "tags":[
      "boho",
      "wood",
      "bench"
    ],
    "url":"https:\/\/example.com\/willow-bench",
    "image_url":"https:\/\/via.placeholder.com\/600?text=Willow+Bench",
    "aisle":"B4",
    "bay":"02",
    "qty_on_hand":0
  },
  {
    "sku":"SEA-CHL-105",
    "title":"Dune Dining Chair (2\u2011pack)",
    "category":"Seating",
    "price":159,
    "style":"Coastal",
    "tags":[
      "coastal",
      "rope",
      "dining"
    ],
    "url":"https:\/\/example.com\/dune-chair",
    "image_url":"https:\/\/via.placeholder.com\/600?text=Dune+Dining+Chair",
    "aisle":"B2",
    "bay":"14",
    "qty_on_hand":6
  },
  {
    "sku":"STR-SHF-201",
    "title":"Hexline Wall Shelf",
    "category":"Storage",
    "price":49,
    "style":"Modern",
    "tags":[
      "modern",
      "shelf",
      "wall"
    ],
    "url":"https:\/\/example.com\/hexline-shelf",
    "image_url":"https:\/\/via.placeholder.com\/600?text=Hexline+Wall+Shelf",
    "aisle":"C1",
    "bay":"05",
    "qty_on_hand":10
  },
  {
    "sku":"STR-CAB-202",
    "title":"Atlas Utility Cabinet",
    "category":"Storage",
    "price":179,
    "style":"Industrial",
    "tags":[
      "industrial",
      "cabinet",
      "steel"
    ],
    "url":"https:\/\/example.com\/atlas-cabinet",
    "image_url":"https:\/\/via.placeholder.com\/600?text=Atlas+Utility+Cabinet",
    "aisle":"C2",
    "bay":"01",
    "qty_on_hand":2
  },
  {
    "sku":"STR-BIN-203",
    "title":"Breeze Woven Bins (set of 3)",
    "category":"Storage",
    "price":39,
    "style":"Coastal",
    "tags":[
      "coastal",
      "woven",
      "bins"
    ],
    "url":"https:\/\/example.com\/breeze-bins",
    "image_url":"https:\/\/via.placeholder.com\/600?text=Breeze+Woven+Bins",
    "aisle":"C3",
    "bay":"07",
    "qty_on_hand":9
  },
  {
    "sku":"STR-BOK-204",
    "title":"Ivy Bookcase",
    "category":"Storage",
    "price":149,
    "style":"Minimalist",
    "tags":[
      "minimalist",
      "bookcase",
      "wood"
    ],
    "url":"https:\/\/example.com\/ivy-bookcase",
    "image_url":"https:\/\/via.placeholder.com\/600?text=Ivy+Bookcase",
    "aisle":"C1",
    "bay":"12",
    "qty_on_hand":0
  },
  {
    "sku":"STR-CRT-205",
    "title":"Rivet Rolling Cart",
    "category":"Storage",
    "price":99,
    "style":"Industrial",
    "tags":[
      "industrial",
      "cart",
      "rolling"
    ],
    "url":"https:\/\/example.com\/rivet-cart",
    "image_url":"https:\/\/via.placeholder.com\/600?text=Rivet+Rolling+Cart",
    "aisle":"C4",
    "bay":"03",
    "qty_on_hand":5
  },
  {
    "sku":"DEC-RUG-301",
    "title":"Grit & Glow Area Rug 5x7",
    "category":"Decor",
    "price":129,
    "style":"Boho",
    "tags":[
      "boho",
      "rug",
      "5x7"
    ],
    "url":"https:\/\/example.com\/gritglow-rug",
    "image_url":"https:\/\/via.placeholder.com\/600?text=Grit+%26+Glow+Rug",
    "aisle":"D2",
    "bay":"09",
    "qty_on_hand":3
  },
  {
    "sku":"DEC-MRR-302",
    "title":"Harbor Round Mirror",
    "category":"Decor",
    "price":79,
    "style":"Coastal",
    "tags":[
      "coastal",
      "mirror",
      "round"
    ],
    "url":"https:\/\/example.com\/harbor-mirror",
    "image_url":"https:\/\/via.placeholder.com\/600?text=Harbor+Round+Mirror",
    "aisle":"D1",
    "bay":"02",
    "qty_on_hand":8
  },
  {
    "sku":"DEC-VSE-303",
    "title":"Bolt Stone Vase",
    "category":"Decor",
    "price":29,
    "style":"Minimalist",
    "tags":[
      "minimalist",
      "vase",
      "stone"
    ],
    "url":"https:\/\/example.com\/bolt-vase",
    "image_url":"https:\/\/via.placeholder.com\/600?text=Bolt+Stone+Vase",
    "aisle":"D3",
    "bay":"06",
    "qty_on_hand":15
  },
  {
    "sku":"DEC-ART-304",
    "title":"Ridge Abstract Print",
    "category":"Decor",
    "price":59,
    "style":"Modern",
    "tags":[
      "modern",
      "print",
      "abstract"
    ],
    "url":"https:\/\/example.com\/ridge-print",
    "image_url":"https:\/\/via.placeholder.com\/600?text=Ridge+Abstract+Print",
    "aisle":"D1",
    "bay":"11",
    "qty_on_hand":0
  },
  {
    "sku":"DEC-CND-305",
    "title":"Timber Candle Trio",
    "category":"Decor",
    "price":24,
    "style":"Cozy",
    "tags":[
      "cozy",
      "candle",
      "set"
    ],
    "url":"https:\/\/example.com\/timber-candles",
    "image_url":"https:\/\/via.placeholder.com\/600?text=Timber+Candle+Trio",
    "aisle":"D4",
    "bay":"01",
    "qty_on_hand":20
  },
  {
    "sku":"OUT-CHR-401",
    "title":"Trailhead Adirondack Chair",
    "category":"Outdoor",
    "price":149,
    "style":"Rustic",
    "tags":[
      "outdoor",
      "chair",
      "adirondack"
    ],
    "url":"https:\/\/example.com\/trailhead-chair",
    "image_url":"https:\/\/via.placeholder.com\/600?text=Trailhead+Adirondack",
    "aisle":"E1",
    "bay":"10",
    "qty_on_hand":6
  },
  {
    "sku":"OUT-LGT-402",
    "title":"Solar Path Lights (4\u2011pack)",
    "category":"Outdoor",
    "price":39,
    "style":"Modern",
    "tags":[
      "outdoor",
      "solar",
      "lights"
    ],
    "url":"https:\/\/example.com\/solar-path",
    "image_url":"https:\/\/via.placeholder.com\/600?text=Solar+Path+Lights",
    "aisle":"E2",
    "bay":"04",
    "qty_on_hand":18
  },
  {
    "sku":"OUT-PIL-403",
    "title":"Coast Outdoor Cushion",
    "category":"Outdoor",
    "price":25,
    "style":"Coastal",
    "tags":[
      "outdoor",
      "cushion",
      "water-resistant"
    ],
    "url":"https:\/\/example.com\/coast-cushion",
    "image_url":"https:\/\/via.placeholder.com\/600?text=Coast+Outdoor+Cushion",
    "aisle":"E3",
    "bay":"05",
    "qty_on_hand":11
  },
  {
    "sku":"OUT-TBL-404",
    "title":"Rivet Bistro Table",
    "category":"Outdoor",
    "price":99,
    "style":"Industrial",
    "tags":[
      "outdoor",
      "table",
      "steel"
    ],
    "url":"https:\/\/example.com\/rivet-bistro",
    "image_url":"https:\/\/via.placeholder.com\/600?text=Rivet+Bistro+Table",
    "aisle":"E1",
    "bay":"02",
    "qty_on_hand":0
  },
  {
    "sku":"OUT-PLN-405",
    "title":"Ivy Planter Set (3)",
    "category":"Outdoor",
    "price":45,
    "style":"Minimalist",
    "tags":[
      "outdoor",
      "planter",
      "set"
    ],
    "url":"https:\/\/example.com\/ivy-planter",
    "image_url":"https:\/\/via.placeholder.com\/600?text=Ivy+Planter+Set",
    "aisle":"E4",
    "bay":"07",
    "qty_on_hand":9
  }
]